{
  "ChimeriaSetup": {
    "narrativeData": [
      "topic",
      "topic-type",
      "passengerStatus",
      {
        "narrativeDatum": "currentState",
        "wildcard": "p"
      },
      "theme",
      "themeDescription",
      "interactiveClause"
    ],
    "categoryFeatures": [
      {
        "rangeFeature": "Assertiveness",
        "labels": {
          "passive": [
            0,
            30
          ],
          "neutral": [
            30,
            70
          ],
          "assertive": [
            70,
            100
          ]
        }
      },
      {
        "rangeFeature": "RacialAwareness",
        "labels": {
          "oblivious": [
            0,
            30
          ],
          "neutral": [
            30,
            70
          ],
          "preparedForBias": [
            70,
            100
          ]
        }
      },
      {
        "rangeFeature": "CulturalAppreciation",
        "labels": {
          "bigotted": [
            0,
            30
          ],
          "neutral": [
            30,
            70
          ],
          "culturallyProud": [
            70,
            100
          ]
        }
      }
    ],
    "categoryPrototypes": {
      "Xenophobic": {
        "RacialAwareness": 5,
        "CulturalAppreciation": 5
      },
      "Multicultural": {
        "RacialAwareness": 90,
        "CulturalAppreciation": 90,
        "Assertiveness": 90
      }
    },
    "abstractCategories": {
      "Ingroup": {
        "wildcard": "X",
        "concreteCategory": "Xenophobic"
      },
      "Outgroup": {
        "wildcard": "O",
        "concreteCategory": "Multicultural"
      }
    },
    "actors": {
      "Marianne": {
        "RacialAwareness": 5,
        "CulturalAppreciation": 0
      },
      "You": {
        "player": "true",
        "Assertiveness": 50,
        "RacialAwareness": 70,
        "CulturalAppreciation": 70
      }
    },
    "substitutes": {

    },
    "narrativeStructure": {
      "main": [
        "orient1",
        "clause0",
        "clause1",
        "clause2",
        "clause3_d1",
        "membershipEvaluation",
        "naturalizationEvaluation",
        "clause4",
        "clause5",
        "clause6",
        "clause7_d2",
        "membershipEvaluation",
        "naturalizationEvaluation",
        "clause8",
        "entrance",
        "clause10",
        "entrance",
        "clause12",
        "entrance",
        "clause14",
        "clause15",
        "clause16",
        "entrance",
        "clause18",
        "clause19_d3",
        "membershipEvaluation",
        "naturalizationEvaluation",
        "clause20",
        "clause21",
        "clause22",
        "clause23_d4",
        "membershipEvaluation",
        "naturalizationEvaluation",
        "clause24",
        "entrance",
        "clause26",
        "entrance",
        "clause28",
        "clause29",
        "conclusion",
        "coda",
        "questionnaire"
      ]
    }
  },
  "orient1": {
    "clause": "orientation",
    "actor": "narrator",
    "content": [
      {
        "narrating": "Over the weekend, you visited friends in Chicago. You just took your seat, hoping that you can complete just one trip without anyone pointing you out for how you look. You are just looking around as you listen to a boarding announcement. A woman just took the seat on the other side of the aisle, and you smiled at her as she settled in."
      }
    ],
    "currentState": "noninteractive"
  },
  "clause0": {
    "clause": "narrative",
    "actor": "Marianne",
    "content": [
      {
        "speaking": "Hi there, I love your scarf thing! To be honest, I would never be able to cover my hair like that."
      }
    ]
  },
  "clause1": {
    "clause": "narrative",
    "actor": "You",
    "content": [
      {
        "speaking": "It’s actually called a hijab. You’d look just fine with your hair covered or not, but I don’t just wear it for fashion."
      }
    ]
  },
  "clause2": {
    "clause": "narrative",
    "actor": "Marianne",
    "content": [
      {
        "speaking": "But isn’t it too warm for this time of year?"
      }
    ]
  },
  "clause3_d1": {
    "clause": "decision",
    "actor": "You",
    "content": [
      {
        "expressing": "Choose what you want to say"
      }
    ],
    "choices": [
      {
        "content": [
          {
            "speaking": "Oh, you must be thinking it’s synthetic, no this is a breathable fabric!"
          }
        ],
        "fallouts": [
          {
            "type": "moveActorFeatureRelativeToCategory",
            "category": "Ingroup",
            "actor": "You",
            "RacialAwareness": 20
          },
          {
            "type": "moveActorFeatureRelativeToCategory",
            "category": "Ingroup",
            "actor": "You",
            "CulturalAppreciation": 20
          },
          {
            "type": "incrementActorFeatureValue",
            "actor": "You",
            "feature": "Assertiveness",
            "delta": -12
          }
        ]
      },
      {
        "content": [
          {
            "speaking": "But there’s AC on the plane and I wear it year round anyway. I don’t see why my hijab would make me too hot."
          }
        ],
        "fallouts": [
          {
            "type": "moveActorFeatureRelativeToCategory",
            "category": "Ingroup",
            "actor": "You",
            "RacialAwareness": 10
          },
          {
            "type": "moveActorFeatureRelativeToCategory",
            "category": "Ingroup",
            "actor": "You",
            "CulturalAppreciation": 10
          },
          {
            "type": "incrementActorFeatureValue",
            "actor": "You",
            "feature": "Assertiveness",
            "delta": -6
          }
        ]
      },
      {
        "content": [
          {
            "speaking": "Oh, you’re really concerned… I have an idea why you’re asking me this."
          }
        ],
        "fallouts": [
          {
            "type": "moveActorFeatureRelativeToCategory",
            "category": "Outgroup",
            "actor": "You",
            "RacialAwareness": 10
          },
          {
            "type": "moveActorFeatureRelativeToCategory",
            "category": "Outgroup",
            "actor": "You",
            "CulturalAppreciation": 10
          },
          {
            "type": "incrementActorFeatureValue",
            "actor": "You",
            "feature": "Assertiveness",
            "delta": 6
          }
        ]
      },
      {
        "content": [
          {
            "speaking": "I wear it all year round just like many Muslim women. You know what they say: You do you, I do me."
          }
        ],
        "fallouts": [
          {
            "type": "moveActorFeatureRelativeToCategory",
            "category": "Outgroup",
            "actor": "You",
            "RacialAwareness": 20
          },
          {
            "type": "moveActorFeatureRelativeToCategory",
            "category": "Outgroup",
            "actor": "You",
            "CulturalAppreciation": 20
          },
          {
            "type": "incrementActorFeatureValue",
            "actor": "You",
            "feature": "Assertiveness",
            "delta": 12
          }
        ]
      }
    ]
  },
  "clause4": {
    "clause": "narrative",
    "actor": "Marianne",
    "content": [
      {
        "speaking": "By the way, my name is Marianne. What is yours?"
      }
    ]
  },
  "clause5": {
    "clause": "narrative",
    "actor": "You",
    "content": [
      {
        "speaking": "I’m Sarah. Nice to meet you."
      }
    ]
  },
  "clause6": {
    "clause": "narrative",
    "actor": "Marianne",
    "content": [
      {
        "speaking": "Sarah? Is that a nickname that’s easier to pronounce than your real name? You can tell me your real one."
      }
    ]
  },
  "clause7_d2": {
    "clause": "decision",
    "actor": "You",
    "content": [
      {
        "expressing": "Choose what you want to say"
      }
    ],
    "choices": [
      {
        "content": [
          {
            "speaking": "Oh, that is my real name! (pleasantly), it’s common in many places!"
          }
        ],
        "fallouts": [
          {
            "type": "moveActorFeatureRelativeToCategory",
            "category": "Ingroup",
            "actor": "You",
            "RacialAwareness": 20
          },
          {
            "type": "moveActorFeatureRelativeToCategory",
            "category": "Ingroup",
            "actor": "You",
            "CulturalAppreciation": 20
          },
          {
            "type": "incrementActorFeatureValue",
            "actor": "You",
            "feature": "Assertiveness",
            "delta": -12
          }
        ]
      },
      {
        "content": [
          {
            "speaking": "Why do you ask? I don’t see why Sarah can’t be my real name."
          }
        ],
        "fallouts": [
          {
            "type": "moveActorFeatureRelativeToCategory",
            "category": "Ingroup",
            "actor": "You",
            "RacialAwareness": 10
          },
          {
            "type": "moveActorFeatureRelativeToCategory",
            "category": "Ingroup",
            "actor": "You",
            "CulturalAppreciation": 10
          },
          {
            "type": "incrementActorFeatureValue",
            "actor": "You",
            "feature": "Assertiveness",
            "delta": -6
          }
        ]
      },
      {
        "content": [
          {
            "speaking": "I feel like I know why you ask, but it’s my real name."
          }
        ],
        "fallouts": [
          {
            "type": "moveActorFeatureRelativeToCategory",
            "category": "Outgroup",
            "actor": "You",
            "RacialAwareness": 10
          },
          {
            "type": "moveActorFeatureRelativeToCategory",
            "category": "Outgroup",
            "actor": "You",
            "CulturalAppreciation": 10
          },
          {
            "type": "incrementActorFeatureValue",
            "actor": "You",
            "feature": "Assertiveness",
            "delta": 6
          }
        ]
      },
      {
        "content": [
          {
            "speaking": "Sarah is my real name. For all I know Marianne may be hard to pronounce for some people."
          }
        ],
        "fallouts": [
          {
            "type": "moveActorFeatureRelativeToCategory",
            "category": "Outgroup",
            "actor": "You",
            "RacialAwareness": 20
          },
          {
            "type": "moveActorFeatureRelativeToCategory",
            "category": "Outgroup",
            "actor": "You",
            "CulturalAppreciation": 20
          },
          {
            "type": "incrementActorFeatureValue",
            "actor": "You",
            "feature": "Assertiveness",
            "delta": 12
          }
        ]
      }
    ]
  },
  "clause8": {
    "clause": "narrative",
    "actor": "Marianne",
    "content": [
      {
        "speaking": "Huh... That’s interesting. You don’t even have an accent! Where did you learn English?"
      }
    ],
    "currentState": "clause9"
  },
  "clause9a": {
    "clause": "entrance",
    "actor": "You",
    "content": [
      {
        "speaking": "Oh… in the Indianapolis school system, I suppose?"
      }
    ],
    "tests": [
      {
        "type": "featureLabel",
        "feature": "Assertiveness",
        "actor": "You",
        "label": "assertive"
      },
      {
        "type": "narrativeDatum",
        "name": "currentState",
        "value": "clause9"
      }
    ],
    "currentState": "noninteractive"
  },
  "clause9b": {
    "clause": "entrance",
    "actor": "You",
    "content": [
      {
        "speaking": "In the Indianapolis school system."
      }
    ],
    "tests": [
      {
        "type": "featureLabel",
        "feature": "Assertiveness",
        "actor": "You",
        "label": "neutral"
      },
      {
        "type": "narrativeDatum",
        "name": "currentState",
        "value": "clause9"
      }
    ],
    "currentState": "noninteractive"
  },
  "clause9c": {
    "clause": "entrance",
    "actor": "You",
    "content": [
      {
        "speaking": "Thank you. I learned English in the Indianapolis school system."
      }
    ],
    "tests": [
      {
        "type": "featureLabel",
        "feature": "Assertiveness",
        "actor": "You",
        "label": "passive"
      },
      {
        "type": "narrativeDatum",
        "name": "currentState",
        "value": "clause9"
      }
    ],
    "currentState": "noninteractive"
  },
  "clause10": {
    "clause": "narrative",
    "actor": "Marianne",
    "content": [
      {
        "speaking": "That’s just here! How come? Where are you from?"
      }
    ],
    "currentState": "clause11"
  },
  "clause11a": {
    "clause": "entrance",
    "actor": "You",
    "content": [
      {
        "speaking": "I’m not sure why it’s so surprising to you, but I’m from Indianapolis."
      }
    ],
    "tests": [
      {
        "type": "featureLabel",
        "feature": "Assertiveness",
        "actor": "You",
        "label": "assertive"
      },
      {
        "type": "narrativeDatum",
        "name": "currentState",
        "value": "clause11"
      }
    ],
    "currentState": "noninteractive"
  },
  "clause11b": {
    "clause": "entrance",
    "actor": "You",
    "content": [
      {
        "speaking": "I’m from Indianapolis."
      }
    ],
    "tests": [
      {
        "type": "featureLabel",
        "feature": "Assertiveness",
        "actor": "You",
        "label": "neutral"
      },
      {
        "type": "narrativeDatum",
        "name": "currentState",
        "value": "clause11"
      }
    ],
    "currentState": "noninteractive"
  },
  "clause11c": {
    "clause": "entrance",
    "actor": "You",
    "content": [
      {
        "speaking": "I know! I’m from Indianapolis."
      }
    ],
    "tests": [
      {
        "type": "featureLabel",
        "feature": "Assertiveness",
        "actor": "You",
        "label": "passive"
      },
      {
        "type": "narrativeDatum",
        "name": "currentState",
        "value": "clause11"
      }
    ],
    "currentState": "noninteractive"
  },
  "clause12": {
    "clause": "narrative",
    "actor": "Marianne",
    "content": [
      {
        "speaking": "No, no, I mean where are you really from? Originally?"
      }
    ],
    "currentState": "clause13"
  },
  "clause13a": {
    "clause": "entrance",
    "actor": "You",
    "content": [
      {
        "speaking": "I was born here in Indianapolis if that’s what you are asking."
      }
    ],
    "tests": [
      {
        "type": "featureLabel",
        "feature": "Assertiveness",
        "actor": "You",
        "label": "assertive"
      },
      {
        "type": "narrativeDatum",
        "name": "currentState",
        "value": "clause13"
      }
    ],
    "currentState": "noninteractive"
  },
  "clause13b": {
    "clause": "entrance",
    "actor": "You",
    "content": [
      {
        "speaking": "I was born in Indianapolis."
      }
    ],
    "tests": [
      {
        "type": "featureLabel",
        "feature": "Assertiveness",
        "actor": "You",
        "label": "neutral"
      },
      {
        "type": "narrativeDatum",
        "name": "currentState",
        "value": "clause13"
      }
    ],
    "currentState": "noninteractive"
  },
  "clause13c": {
    "clause": "entrance",
    "actor": "You",
    "content": [
      {
        "speaking": "I am originally from Indianapolis but have lived in West Lafayette for a long time. It feels like my hometown now."
      }
    ],
    "tests": [
      {
        "type": "featureLabel",
        "feature": "Assertiveness",
        "actor": "You",
        "label": "passive"
      },
      {
        "type": "narrativeDatum",
        "name": "currentState",
        "value": "clause13"
      }
    ],
    "currentState": "noninteractive"
  },
  "clause14": {
    "clause": "narrative",
    "actor": "Marianne",
    "content": [
      {
        "speaking": "I mean your family. Where are they from?"
      }
    ]
  },
  "clause15": {
    "clause": "narrative",
    "actor": "You",
    "content": [
      {
        "speaking": "My grandparents immigrated to the US from Malaysia and moved to Indiana for work."
      }
    ]
  },
  "clause16": {
    "clause": "narrative",
    "actor": "Marianne",
    "content": [
      {
        "speaking": "To work as farmworkers? Indiana does have a lot of farms!"
      }
    ],
    "currentState": "clause17"
  },
  "clause17a": {
    "clause": "entrance",
    "actor": "You",
    "content": [
      {
        "speaking": "No, that’s an oversimplified and incorrect guess. They moved here to teach at Purdue University. Before retiring my grandfather was a chemical engineer and my grandmother was a professor, like me."
      }
    ],
    "tests": [
      {
        "type": "featureLabel",
        "feature": "Assertiveness",
        "actor": "You",
        "label": "assertive"
      },
      {
        "type": "narrativeDatum",
        "name": "currentState",
        "value": "clause17"
      }
    ],
    "currentState": "noninteractive"
  },
  "clause17b": {
    "clause": "entrance",
    "actor": "You",
    "content": [
      {
        "speaking": "To teach at Purdue University, actually. Before retiring my grandfather was a chemical engineer and my grandmother was a professor, like me."
      }
    ],
    "tests": [
      {
        "type": "featureLabel",
        "feature": "Assertiveness",
        "actor": "You",
        "label": "neutral"
      },
      {
        "type": "narrativeDatum",
        "name": "currentState",
        "value": "clause17"
      }
    ],
    "currentState": "noninteractive"
  },
  "clause17c": {
    "clause": "entrance",
    "actor": "You",
    "content": [
      {
        "speaking": "Agriculture is a big deal in Indiana, indeed! But they moved here to teach at Purdue University, actually. Before retiring my grandfather was a chemical engineer and my grandmother was a professor, like me."
      }
    ],
    "tests": [
      {
        "type": "featureLabel",
        "feature": "Assertiveness",
        "actor": "You",
        "label": "passive"
      },
      {
        "type": "narrativeDatum",
        "name": "currentState",
        "value": "clause17"
      }
    ],
    "currentState": "noninteractive"
  },
  "clause18": {
    "clause": "narrative",
    "actor": "Marianne",
    "content": [
      {
        "speaking": "You're a professor?",
        "expressing": "shocked"
      }
    ]
  },
  "clause19_d3": {
    "clause": "decision",
    "actor": "You",
    "content": [
      {
        "expressing": "Choose what you want to say"
      }
    ],
    "choices": [
      {
        "content": [
          {
            "speaking": "I know I don't look like it. (shyly)"
          }
        ],
        "fallouts": [
          {
            "type": "moveActorFeatureRelativeToCategory",
            "category": "Ingroup",
            "actor": "You",
            "RacialAwareness": 20
          },
          {
            "type": "moveActorFeatureRelativeToCategory",
            "category": "Ingroup",
            "actor": "You",
            "CulturalAppreciation": 20
          },
          {
            "type": "incrementActorFeatureValue",
            "actor": "You",
            "feature": "Assertiveness",
            "delta": -12
          }
        ]
      },
      {
        "content": [
          {
            "speaking": "Yes. Maybe you are not used to seeing professors outside academic settings. It’s just another job."
          }
        ],
        "fallouts": [
          {
            "type": "moveActorFeatureRelativeToCategory",
            "category": "Ingroup",
            "actor": "You",
            "RacialAwareness": 10
          },
          {
            "type": "moveActorFeatureRelativeToCategory",
            "category": "Ingroup",
            "actor": "You",
            "CulturalAppreciation": 10
          },
          {
            "type": "incrementActorFeatureValue",
            "actor": "You",
            "feature": "Assertiveness",
            "delta": -6
          }
        ]
      },
      {
        "content": [
          {
            "speaking": "It seems like it’s surprising to you, and I think I know why. Yes, I am a professor."
          }
        ],
        "fallouts": [
          {
            "type": "moveActorFeatureRelativeToCategory",
            "category": "Outgroup",
            "actor": "You",
            "RacialAwareness": 10
          },
          {
            "type": "moveActorFeatureRelativeToCategory",
            "category": "Outgroup",
            "actor": "You",
            "CulturalAppreciation": 10
          },
          {
            "type": "incrementActorFeatureValue",
            "actor": "You",
            "feature": "Assertiveness",
            "delta": 6
          }
        ]
      },
      {
        "content": [
          {
            "speaking": "Maybe you don’t know a lot of people in higher ed, but yes, I am in fact a professor."
          }
        ],
        "fallouts": [
          {
            "type": "moveActorFeatureRelativeToCategory",
            "category": "Outgroup",
            "actor": "You",
            "RacialAwareness": 20
          },
          {
            "type": "moveActorFeatureRelativeToCategory",
            "category": "Outgroup",
            "actor": "You",
            "CulturalAppreciation": 20
          },
          {
            "type": "incrementActorFeatureValue",
            "actor": "You",
            "feature": "Assertiveness",
            "delta": 12
          }
        ]
      }
    ]
  },
  "clause20": {
    "clause": "narrative",
    "actor": "Marianne",
    "content": [
      {
        "speaking": "What do you teach?"
      }
    ]
  },
  "clause21": {
    "clause": "narrative",
    "actor": "You",
    "content": [
      {
        "speaking": "Philosophy."
      }
    ]
  },
  "clause22": {
    "clause": "narrative",
    "actor": "Marianne",
    "content": [
      {
        "speaking": "Oh wow! One of my sons is very interested in philosophy. He studies computer science but is doing a minor in philosophy.\n\nWe have two boys. You’ve probably had to have a lot—six? Seven?\n\n"
      }
    ]
  },
  "clause23_d4": {
    "clause": "decision",
    "actor": "You",
    "content": [
      {
        "expressing": "Choose what you want to say"
      }
    ],
    "choices": [
      {
        "content": [
          {
            "speaking": "Haha, I see what you mean, but I have two boys too."
          }
        ],
        "fallouts": [
          {
            "type": "moveActorFeatureRelativeToCategory",
            "category": "Ingroup",
            "actor": "You",
            "RacialAwareness": 20
          },
          {
            "type": "moveActorFeatureRelativeToCategory",
            "category": "Ingroup",
            "actor": "You",
            "CulturalAppreciation": 20
          },
          {
            "type": "incrementActorFeatureValue",
            "actor": "You",
            "feature": "Assertiveness",
            "delta": -12
          }
        ]
      },
      {
        "content": [
          {
            "speaking": "That’s perhaps your impression of families in Indiana, but I have two boys, as well."
          }
        ],
        "fallouts": [
          {
            "type": "moveActorFeatureRelativeToCategory",
            "category": "Ingroup",
            "actor": "You",
            "RacialAwareness": 10
          },
          {
            "type": "moveActorFeatureRelativeToCategory",
            "category": "Ingroup",
            "actor": "You",
            "CulturalAppreciation": 10
          },
          {
            "type": "incrementActorFeatureValue",
            "actor": "You",
            "feature": "Assertiveness",
            "delta": -6
          }
        ]
      },
      {
        "content": [
          {
            "speaking": "I probably see where you are going with this, but I have two boys only."
          }
        ],
        "fallouts": [
          {
            "type": "moveActorFeatureRelativeToCategory",
            "category": "Outgroup",
            "actor": "You",
            "RacialAwareness": 10
          },
          {
            "type": "moveActorFeatureRelativeToCategory",
            "category": "Outgroup",
            "actor": "You",
            "CulturalAppreciation": 10
          },
          {
            "type": "incrementActorFeatureValue",
            "actor": "You",
            "feature": "Assertiveness",
            "delta": 6
          }
        ]
      },
      {
        "content": [
          {
            "speaking": "No. I, too, have two boys, just like you."
          }
        ],
        "fallouts": [
          {
            "type": "moveActorFeatureRelativeToCategory",
            "category": "Outgroup",
            "actor": "You",
            "RacialAwareness": 20
          },
          {
            "type": "moveActorFeatureRelativeToCategory",
            "category": "Outgroup",
            "actor": "You",
            "CulturalAppreciation": 20
          },
          {
            "type": "incrementActorFeatureValue",
            "actor": "You",
            "feature": "Assertiveness",
            "delta": 12
          }
        ]
      }
    ]
  },
  "clause24": {
    "clause": "narrative",
    "actor": "Marianne",
    "content": [
      {
        "speaking": "Huh, it sounds like your husband has adapted to American culture very well. Good for you!\n\nFamily is important. As a matter of fact, I was just visiting my older son in Chicago."
      }
    ],
    "currentState": "clause25"
  },
  "clause25a": {
    "clause": "entrance",
    "actor": "You",
    "content": [
      {
        "speaking": "My husband didn’t need to adapt to American culture; he was born here in the US."
      }
    ],
    "tests": [
      {
        "type": "featureLabel",
        "feature": "Assertiveness",
        "actor": "You",
        "label": "assertive"
      },
      {
        "type": "narrativeDatum",
        "name": "currentState",
        "value": "clause25"
      }
    ],
    "currentState": "noninteractive"
  },
  "clause25b": {
    "clause": "entrance",
    "actor": "You",
    "content": [
      {
        "speaking": "Actually, my husband was born here in the US."
      }
    ],
    "tests": [
      {
        "type": "featureLabel",
        "feature": "Assertiveness",
        "actor": "You",
        "label": "neutral"
      },
      {
        "type": "narrativeDatum",
        "name": "currentState",
        "value": "clause25"
      }
    ],
    "currentState": "noninteractive"
  },
  "clause25c": {
    "clause": "entrance",
    "actor": "You",
    "content": [
      {
        "speaking": "Thanks, but he was born here in the US."
      }
    ],
    "tests": [
      {
        "type": "featureLabel",
        "feature": "Assertiveness",
        "actor": "You",
        "label": "passive"
      },
      {
        "type": "narrativeDatum",
        "name": "currentState",
        "value": "clause25"
      }
    ],
    "currentState": "noninteractive"
  },
  "clause26": {
    "clause": "narrative",
    "actor": "Marianne",
    "content": [
      {
        "speaking": "Interesting… Where did you say you taught?"
      }
    ],
    "currentState": "clause27"
  },
  "clause27a": {
    "clause": "entrance",
    "actor": "You",
    "content": [
      {
        "speaking": "I didn’t. But I teach at Indiana University."
      }
    ],
    "tests": [
      {
        "type": "featureLabel",
        "feature": "Assertiveness",
        "actor": "You",
        "label": "assertive"
      },
      {
        "type": "narrativeDatum",
        "name": "currentState",
        "value": "clause27"
      }
    ],
    "currentState": "noninteractive"
  },
  "clause27b": {
    "clause": "entrance",
    "actor": "You",
    "content": [
      {
        "speaking": "I teach at Indiana University."
      }
    ],
    "tests": [
      {
        "type": "featureLabel",
        "feature": "Assertiveness",
        "actor": "You",
        "label": "neutral"
      },
      {
        "type": "narrativeDatum",
        "name": "currentState",
        "value": "clause27"
      }
    ],
    "currentState": "noninteractive"
  },
  "clause27c": {
    "clause": "entrance",
    "actor": "You",
    "content": [
      {
        "speaking": "I am fortunate enough to teach at Indiana University."
      }
    ],
    "tests": [
      {
        "type": "featureLabel",
        "feature": "Assertiveness",
        "actor": "You",
        "label": "passive"
      },
      {
        "type": "narrativeDatum",
        "name": "currentState",
        "value": "clause27"
      }
    ],
    "currentState": "noninteractive"
  },
  "clause28": {
    "clause": "narrative",
    "actor": "Marianne",
    "content": [
      {
        "speaking": "No way! That’s where my younger son goes! He is actually a research assistant for a professor in the AI Ethics Institute at the university. I don’t quite understand what they do, but he just cannot stop talking about a Dr. Shah. He seems to enjoy working with her."
      }
    ]
  },
  "clause29": {
    "clause": "narrative",
    "actor": "You",
    "content": [
      {
        "speaking": "Well, any chance you are talking about Jason? I ask because I’m Dr. Shah. My full name is Sarah Shah, and I am the only Dr. Shah in our department."
      }
    ],
    "currentState": "clause30"
  },
  "clause30a": {
    "clause": "conclusion",
    "actor": "Marianne",
    "content": [
      {
        "speaking": "Holy moly! Yes, I am. It’s a great pleasure to meet you Dr. Shah. Our son is very fond of you and your amazing work! He is so lucky to have a fellow Hoosier as a professor."
      }
    ],
    "tests": [
      {
        "type": "categoryMembership",
        "category": "Ingroup",
        "range": [
          50,
          100
        ],
        "actor": "You"
      },
      {
        "type": "naturalizationTrajectory",
        "category": "Ingroup",
        "direction": "increasing",
        "actor": "You"
      },
      {
        "type": "narrativeDatum",
        "name": "currentState",
        "value": "clause30"
      }
    ],
    "currentState": "noninteractive"
  },
  "clause30b": {
    "clause": "conclusion",
    "actor": "Marianne",
    "content": [
      {
        "speaking": "Yes, he is my son. Nice to meet you, Dr. Shah. Jason seems to enjoy his work with you. Despite everything else, it’s lucky for him to work with a professor from Indiana."
      }
    ],
    "tests": [
      {
        "type": "categoryMembership",
        "category": "Ingroup",
        "range": [
          50,
          100
        ],
        "actor": "You"
      },
      {
        "type": "naturalizationTrajectory",
        "category": "Ingroup",
        "direction": "decreasing",
        "actor": "You"
      },
      {
        "type": "narrativeDatum",
        "name": "currentState",
        "value": "clause30"
      }
    ],
    "currentState": "noninteractive"
  },
  "clause30c": {
    "clause": "conclusion",
    "actor": "Marianne",
    "content": [
      {
        "speaking": "Yes, I am. Nice to meet you, Dr. Shah. Our son seems to enjoy working with you. It is interesting for him to have a professor who is also from Indiana."
      }
    ],
    "tests": [
      {
        "type": "categoryMembership",
        "category": "Ingroup",
        "range": [
          50,
          100
        ],
        "actor": "You"
      },
      {
        "type": "naturalizationTrajectory",
        "category": "Ingroup",
        "direction": "fluctuating",
        "actor": "You"
      },
      {
        "type": "narrativeDatum",
        "name": "currentState",
        "value": "clause30"
      }
    ],
    "currentState": "noninteractive"
  },
  "clause30d": {
    "clause": "conclusion",
    "actor": "Marianne",
    "content": [
      {
        "speaking": "This is a rather interesting twist of fate, but yes, he is my son. Despite the unusual circumstances, he seems to be enjoying his work. Let’s just hope he benefits from working with someone like you."
      }
    ],
    "tests": [
      {
        "type": "categoryMembership",
        "category": "Ingroup",
        "range": [
          0,
          50
        ],
        "actor": "You"
      },
      {
        "type": "naturalizationTrajectory",
        "category": "Ingroup",
        "direction": "increasing",
        "actor": "You"
      },
      {
        "type": "narrativeDatum",
        "name": "currentState",
        "value": "clause30"
      }
    ],
    "currentState": "noninteractive"
  },
  "clause30e": {
    "clause": "conclusion",
    "actor": "Marianne",
    "content": [
      {
        "speaking": "Huh, that’s unbelievable, but yes, he is my son. Life works in mysterious ways, apparently. It is interesting for him to have a professor like you. The university must be hiring faculty from all over the world."
      }
    ],
    "tests": [
      {
        "type": "categoryMembership",
        "category": "Ingroup",
        "range": [
          0,
          50
        ],
        "actor": "You"
      },
      {
        "type": "naturalizationTrajectory",
        "category": "Ingroup",
        "direction": "decreasing",
        "actor": "You"
      },
      {
        "type": "narrativeDatum",
        "name": "currentState",
        "value": "clause30"
      }
    ],
    "currentState": "noninteractive"
  },
  "clause30f": {
    "clause": "conclusion",
    "actor": "Marianne",
    "content": [
      {
        "speaking": "It’s almost incredible, but, yes Jason is my son. It is interesting for him to have a professor like you. Maybe he will get something out of working with professors from around the world."
      }
    ],
    "tests": [
      {
        "type": "categoryMembership",
        "category": "Ingroup",
        "range": [
          0,
          50
        ],
        "actor": "You"
      },
      {
        "type": "naturalizationTrajectory",
        "category": "Ingroup",
        "direction": "fluctuating",
        "actor": "You"
      },
      {
        "type": "narrativeDatum",
        "name": "currentState",
        "value": "clause30"
      }
    ],
    "currentState": "noninteractive"
  },
  "coda1a": {
    "clause": "coda",
    "actor": "You",
    "content": [
      {
        "thinking": "She was convinced that I am an American too. However, I ended up appeasing her to achieve this. I felt like I didn’t really stand up for myself. I feel bad that I even bolstered some of her misconceptions about Muslims."
      }
    ],
    "tests": [
      {
        "type": "categoryMembership",
        "category": "Ingroup",
        "range": [
          50,
          100
        ],
        "actor": "You"
      },
      {
        "type": "naturalizationTrajectory",
        "category": "Ingroup",
        "direction": "increasing",
        "actor": "You"
      }
    ],
    "currentState": "noninteractive"
  },
  "coda1b": {
    "clause": "coda",
    "actor": "You",
    "content": [
      {
        "thinking": "In the end, she was convinced that I am American too. I initially went with the flow and told her what she wanted to hear but didn’t bolster her misconceptions about my Muslim identity."
      }
    ],
    "tests": [
      {
        "type": "categoryMembership",
        "category": "Ingroup",
        "range": [
          50,
          100
        ],
        "actor": "You"
      },
      {
        "type": "naturalizationTrajectory",
        "category": "Ingroup",
        "direction": "decreasing",
        "actor": "You"
      }
    ],
    "currentState": "noninteractive"
  },
  "coda1c": {
    "clause": "coda",
    "actor": "You",
    "content": [
      {
        "thinking": "She was finally convinced that I am an American. She didn’t appear too fond of people like me, though. I should perhaps have been more assertive about my identity as a Muslim American. Sometimes it felt like I was going with the flow to appease her."
      }
    ],
    "tests": [
      {
        "type": "categoryMembership",
        "category": "Ingroup",
        "range": [
          50,
          100
        ],
        "actor": "You"
      },
      {
        "type": "naturalizationTrajectory",
        "category": "Ingroup",
        "direction": "fluctuating",
        "actor": "You"
      }
    ],
    "currentState": "noninteractive"
  },
  "coda1d": {
    "clause": "coda",
    "actor": "You",
    "content": [
      {
        "thinking": "She wasn’t convinced that I was an American, too, even though I did go with the flow from time to time, not standing up against some of her misconceptions about Muslims."
      }
    ],
    "tests": [
      {
        "type": "categoryMembership",
        "category": "Ingroup",
        "range": [
          0,
          50
        ],
        "actor": "You"
      },
      {
        "type": "naturalizationTrajectory",
        "category": "Ingroup",
        "direction": "increasing",
        "actor": "You"
      }
    ],
    "currentState": "noninteractive"
  },
  "coda1e": {
    "clause": "coda",
    "actor": "You",
    "content": [
      {
        "thinking": "She didn’t seem convinced that I could be an American, as well. I don’t care, though, as I am who I am and won’t change that for anyone. Why should my outfit make me “un-American”? I’m glad I was assertive and unapologetic about my Muslim identity. "
      }
    ],
    "tests": [
      {
        "type": "categoryMembership",
        "category": "Ingroup",
        "range": [
          0,
          50
        ],
        "actor": "You"
      },
      {
        "type": "naturalizationTrajectory",
        "category": "Ingroup",
        "direction": "decreasing",
        "actor": "You"
      }
    ],
    "currentState": "noninteractive"
  },
  "coda1f": {
    "clause": "coda",
    "actor": "You",
    "content": [
      {
        "thinking": "She wasn’t quite convinced that I am an American. It doesn’t seem like she welcomes people who look like me as fellow Americans. I feel good that I didn’t give in to her misconceptions about Muslims."
      }
    ],
    "tests": [
      {
        "type": "categoryMembership",
        "category": "Ingroup",
        "range": [
          0,
          50
        ],
        "actor": "You"
      },
      {
        "type": "naturalizationTrajectory",
        "category": "Ingroup",
        "direction": "fluctuating",
        "actor": "You"
      }
    ],
    "currentState": "noninteractive"
  },
  "naturalization1a.1": {
    "clause": "naturalizationEvaluation",
    "actor": "You",
    "tests": [
      {
        "type": "categoryMembershipDelta",
        "category": "Ingroup",
        "range": [
          0.01,
          100
        ],
        "actor": "You"
      },
      {
        "type": "naturalizationTrajectory",
        "category": "Ingroup",
        "direction": "increasing",
        "actor": "You"
      }
    ],
    "content": [
      {
        "thinking": "I’ll just tell you what you want to hear."
      }
    ]
  },
  "naturalization1a.2": {
    "clause": "naturalizationEvaluation",
    "actor": "You",
    "tests": [
      {
        "type": "categoryMembershipDelta",
        "category": "Ingroup",
        "range": [
          0.01,
          100
        ],
        "actor": "You"
      },
      {
        "type": "naturalizationTrajectory",
        "category": "Ingroup",
        "direction": "increasing",
        "actor": "You"
      }
    ],
    "content": [
      {
        "thinking": "I’ll appease you to fit in."
      }
    ]
  },
  "naturalization1b.1": {
    "clause": "naturalizationEvaluation",
    "actor": "You",
    "tests": [
      {
        "type": "categoryMembershipDelta",
        "category": "Ingroup",
        "range": [
          0.01,
          100
        ],
        "actor": "You"
      },
      {
        "type": "naturalizationTrajectory",
        "category": "Ingroup",
        "direction": "decreasing",
        "actor": "You"
      }
    ],
    "content": [
      {
        "thinking": "Maybe that wasn’t precisely what you wanted to hear. "
      }
    ]
  },
  "naturalization1b.2": {
    "clause": "naturalizationEvaluation",
    "actor": "You",
    "tests": [
      {
        "type": "categoryMembershipDelta",
        "category": "Ingroup",
        "range": [
          0.01,
          100
        ],
        "actor": "You"
      },
      {
        "type": "naturalizationTrajectory",
        "category": "Ingroup",
        "direction": "decreasing",
        "actor": "You"
      }
    ],
    "content": [
      {
        "thinking": "Perhaps that wasn't really what you wanted me to say."
      }
    ]
  },
  "naturalization1c.1": {
    "clause": "naturalizationEvaluation",
    "actor": "You",
    "tests": [
      {
        "type": "categoryMembershipDelta",
        "category": "Ingroup",
        "range": [
          0.01,
          100
        ],
        "actor": "You"
      },
      {
        "type": "naturalizationTrajectory",
        "category": "Ingroup",
        "direction": "fluctuating",
        "actor": "You"
      }
    ],
    "content": [
      {
        "thinking": "I just hope this is close to what you want to hear."
      }
    ]
  },
  "naturalization1c.2": {
    "clause": "naturalizationEvaluation",
    "actor": "You",
    "tests": [
      {
        "type": "categoryMembershipDelta",
        "category": "Ingroup",
        "range": [
          0.01,
          100
        ],
        "actor": "You"
      },
      {
        "type": "naturalizationTrajectory",
        "category": "Ingroup",
        "direction": "fluctuating",
        "actor": "You"
      }
    ],
    "content": [
      {
        "thinking": "Let's hope this is close to what you want me to say."
      }
    ]
  },
  "naturalization1d.1": {
    "clause": "naturalizationEvaluation",
    "actor": "You",
    "tests": [
      {
        "type": "categoryMembershipDelta",
        "category": "Ingroup",
        "range": [
          -100,
          0
        ],
        "actor": "You"
      },
      {
        "type": "naturalizationTrajectory",
        "category": "Ingroup",
        "direction": "increasing",
        "actor": "You"
      }
    ],
    "content": [
      {
        "thinking": "I hope this is what you want to hear."
      }
    ]
  },
  "naturalization1d.2": {
    "clause": "naturalizationEvaluation",
    "actor": "You",
    "tests": [
      {
        "type": "categoryMembershipDelta",
        "category": "Ingroup",
        "range": [
          -100,
          0
        ],
        "actor": "You"
      },
      {
        "type": "naturalizationTrajectory",
        "category": "Ingroup",
        "direction": "increasing",
        "actor": "You"
      }
    ],
    "content": [
      {
        "thinking": "Let's just hope this is what you want me to say."
      }
    ]
  },
  "naturalization1e.1": {
    "clause": "naturalizationEvaluation",
    "actor": "You",
    "tests": [
      {
        "type": "categoryMembershipDelta",
        "category": "Ingroup",
        "range": [
          -100,
          0
        ],
        "actor": "You"
      },
      {
        "type": "naturalizationTrajectory",
        "category": "Ingroup",
        "direction": "decreasing",
        "actor": "You"
      }
    ],
    "content": [
      {
        "thinking": "I will not give in to your misconceptions."
      }
    ]
  },
  "naturalization1e.2": {
    "clause": "naturalizationEvaluation",
    "actor": "You",
    "tests": [
      {
        "type": "categoryMembershipDelta",
        "category": "Ingroup",
        "range": [
          -100,
          0
        ],
        "actor": "You"
      },
      {
        "type": "naturalizationTrajectory",
        "category": "Ingroup",
        "direction": "decreasing",
        "actor": "You"
      }
    ],
    "content": [
      {
        "thinking": "I will stand up for myself, no matter what."
      }
    ]
  },
  "naturalization1f.1": {
    "clause": "naturalizationEvaluation",
    "actor": "You",
    "tests": [
      {
        "type": "categoryMembershipDelta",
        "category": "Ingroup",
        "range": [
          -100,
          0
        ],
        "actor": "You"
      },
      {
        "type": "naturalizationTrajectory",
        "category": "Ingroup",
        "direction": "fluctuating",
        "actor": "You"
      }
    ],
    "content": [
      {
        "thinking": "I don’t think this is what you want to hear, but oh well.."
      }
    ]
  },
  "naturalization1f.2": {
    "clause": "naturalizationEvaluation",
    "actor": "You",
    "tests": [
      {
        "type": "categoryMembershipDelta",
        "category": "Ingroup",
        "range": [
          -100,
          0
        ],
        "actor": "You"
      },
      {
        "type": "naturalizationTrajectory",
        "category": "Ingroup",
        "direction": "fluctuating",
        "actor": "You"
      }
    ],
    "content": [
      {
        "thinking": "This may not be what you expected me to say, but anyway…"
      }
    ]
  },
  "membershipEval1a": {
    "clause": "membershipEvaluation",
    "actor": "Marianne",
    "tests": [
      {
        "type": "categoryMembershipDelta",
        "category": "Ingroup",
        "actor": "You",
        "range": [
          0,
          0.5
        ]
      }
    ],
    "content": [
      {
        "expressing": "smilingSlightly"
      }
    ]
  },
  "membershipEval1b": {
    "clause": "membershipEvaluation",
    "actor": "Marianne",
    "tests": [
      {
        "type": "categoryMembershipDelta",
        "category": "Ingroup",
        "actor": "You",
        "range": [
          0.5,
          1
        ]
      }
    ],
    "content": [
      {
        "expressing": "smiling"
      }
    ]
  },
  "membershipEval1c": {
    "clause": "membershipEvaluation",
    "actor": "Marianne",
    "tests": [
      {
        "type": "categoryMembershipDelta",
        "category": "Ingroup",
        "actor": "You",
        "range": [
          1,
          100
        ]
      }
    ],
    "content": [
      {
        "expressing": "smilingBroadly"
      }
    ]
  },
  "membershipEval1d": {
    "clause": "membershipEvaluation",
    "actor": "Marianne",
    "tests": [
      {
        "type": "categoryMembershipDelta",
        "category": "Ingroup",
        "actor": "You",
        "range": [
          -0.5,
          0
        ]
      }
    ],
    "content": [
      {
        "expressing": "frowningSlightly"
      }
    ]
  },
  "membershipEval1e": {
    "clause": "membershipEvaluation",
    "actor": "Marianne",
    "tests": [
      {
        "type": "categoryMembershipDelta",
        "category": "Ingroup",
        "actor": "You",
        "range": [
          -1,
          -0.5
        ]
      }
    ],
    "content": [
      {
        "expressing": "frowning"
      }
    ]
  },
  "membershipEval1f": {
    "clause": "membershipEvaluation",
    "actor": "Marianne",
    "tests": [
      {
        "type": "categoryMembershipDelta",
        "category": "Ingroup",
        "actor": "You",
        "range": [
          -100,
          -1
        ]
      }
    ],
    "content": [
      {
        "expressing": "frowning"
      }
    ]
  },
  "questionnaire": {
    "clause": "orientation",
    "actor": "narrator",
    "content": [
      {
        "narrating": "You are done with the simulation. \n\nNow we would like to ask you a few questions.\n\nPlease proceed to the next step by clicking the > button."
      }
    ],
    "currentState": "noninteractive"
  }
}
